shinyecharts/__init__.py
shinyecharts/_core.py
shinyecharts/chart.py
shinyecharts/experimental.py
shinyecharts/express.py
shinyecharts/options.py
shinyecharts/renderer.py
shinyecharts/srcjs/echarts-bindings.js
shinyecharts/ui.py
shinyecharts-0.1.1.dist-info/LICENSE
shinyecharts-0.1.1.dist-info/METADATA
shinyecharts-0.1.1.dist-info/WHEEL
shinyecharts-0.1.1.dist-info/RECORD
