Metadata-Version: 2.1
Name: shinyecharts
Version: 0.1.1
Summary: ECharts for Shiny
License: MIT
Author: Stefan Kuethe
Author-email: stefan.kuethe@eoda.de
Requires-Python: >=3.9,<4.0
Classifier: License :: OSI Approved :: MIT License
Classifier: Programming Language :: Python :: 3
Classifier: Programming Language :: Python :: 3.9
Classifier: Programming Language :: Python :: 3.10
Classifier: Programming Language :: Python :: 3.11
Classifier: Programming Language :: Python :: 3.12
Requires-Dist: pandas
Requires-Dist: shiny (>=0.7.1,<0.8.0)
